fastapi_telegrambot/__init__.py
fastapi_telegrambot/config.py
fastapi_telegrambot/main.py
fastapi_telegrambot/api/v0/api.py
fastapi_telegrambot/api/v0/endpoints/routes.py
fastapi_telegrambot/telbot/__init__.py
fastapi_telegrambot/telbot/message.py
fastapi_telegrambot-0.24.202402.dist-info/LICENSE
fastapi_telegrambot-0.24.202402.dist-info/METADATA
fastapi_telegrambot-0.24.202402.dist-info/WHEEL
fastapi_telegrambot-0.24.202402.dist-info/top_level.txt
fastapi_telegrambot-0.24.202402.dist-info/RECORD
