Metadata-Version: 2.1
Name: fastapi_telegrambot
Version: 0.24.202402
Summary: TelegramBot wrapped by FastAPI
Author-email: knowidea-k <knowidea.k@gmail.com>
Project-URL: Homepage, https://github.com/knowidea-k/fastapi_telegrambot
Project-URL: Issues, https://github.com/knowidea-k/fastapi_telegrambot/issues
Classifier: Programming Language :: Python :: 3
Classifier: License :: OSI Approved :: MIT License
Classifier: Operating System :: OS Independent
Requires-Python: >=3.8
License-File: LICENSE
